{
  "list": [
    {
      "id": "100101",
      "name": "Synthe_Wheatmeal",
      "description": "小麦粉_合成",
      "build": "100101",
      "time_min": "10",
      "synthe_item_id": "500101",
      "formula_1": [
        "100101",
        "100102"
      ],
      "quality": [
        "2",
        "1"
      ]
    },
    {
      "id": "100102",
      "name": "Synthe_bread",
      "description": "面包_合成",
      "build": "100101",
      "time_min": "30",
      "synthe_item_id": "500102",
      "formula_1": [
        "500101"
      ],
      "quality": [
        "2"
      ]
    },
    {
      "id": "100103",
      "name": "Synthe_StrawberryJam",
      "description": "草莓果酱_合成",
      "build": "100102",
      "time_min": "60",
      "synthe_item_id": "500103",
      "formula_1": [
        "100107"
      ],
      "quality": [
        "5"
      ]
    },
    {
      "id": "100104",
      "name": "Synthe_GrapeJelly",
      "description": "葡萄果酱_合成",
      "build": "100102",
      "time_min": "90",
      "synthe_item_id": "500104",
      "formula_1": [
        "100109"
      ],
      "quality": [
        "5"
      ]
    }
  ]
}